vip_ipykernel_launcher.py
vip_ipykernel/__init__.py
vip_ipykernel/kernelspec.py
vip_ipykernel-1.0.1.post1.dist-info/METADATA
vip_ipykernel-1.0.1.post1.dist-info/WHEEL
vip_ipykernel-1.0.1.post1.dist-info/top_level.txt
vip_ipykernel-1.0.1.post1.dist-info/RECORD
