Metadata-Version: 2.1
Name: vip-ipykernel
Version: 1.0.1.post1
Summary: UNKNOWN
Home-page: https://github.com/RobertRosca/vip-ipykernel
Author: Robert Rosca
Author-email: 32569096+RobertRosca@users.noreply.github.com
License: UNKNOWN
Platform: UNKNOWN
Requires-Python: ==3.*,>=3.6.0
Requires-Dist: jupyter-client (>=4.2)
Requires-Dist: ipykernel (>=4.4)
Provides-Extra: test
Requires-Dist: pytest (==5.*,>=5.2.0) ; extra == 'test'
Requires-Dist: pytest-cov (==2.*,>=2.10.1) ; extra == 'test'
Requires-Dist: nose (==1.*,>=1.3.7) ; extra == 'test'
Requires-Dist: nbval (==0.9.*,>=0.9.6) ; extra == 'test'
